mhpackage/__init__.py
mhpackage-0.1.dist-info/METADATA
mhpackage-0.1.dist-info/WHEEL
mhpackage-0.1.dist-info/top_level.txt
mhpackage-0.1.dist-info/RECORD
