Metadata-Version: 2.1
Name: mhpackage
Version: 0.1
Summary: The mhpackage joke in the world
Home-page: https://job4moshe@dev.azure.com/job4moshe/mhpackageProject/_git/mhpackageProject
Author: Flying Circus
Author-email: job4moshe@gmail.com
License: MIT
Platform: UNKNOWN
